aievals/__ini__.py
aievals/main.py
aievals-0.1.0.dist-info/LICENSE
aievals-0.1.0.dist-info/METADATA
aievals-0.1.0.dist-info/WHEEL
aievals-0.1.0.dist-info/top_level.txt
aievals-0.1.0.dist-info/RECORD
