Metadata-Version: 2.1
Name: aievals
Version: 0.1.0
Summary: experimental AI evaluation tools
Author-email: Your Name <your.email@example.com>
License: MIT License
Project-URL: Homepage, https://github.com/chroma-core/aievals
Project-URL: Bug Tracker, https://github.com/chroma-core/aievals/issues
Classifier: Programming Language :: Python :: 3
Classifier: License :: OSI Approved :: MIT License
Classifier: Operating System :: OS Independent
Requires-Python: >=3.7
License-File: LICENSE
